AUTHORS.rst
CONTRIBUTING.rst
LICENSE
MANIFEST.in
README.rst
requirements.txt
setup.cfg
setup.py
versioneer.py
dian/__init__.py
dian/_version.py
dian/dae.py
dian/math.py
dian/system.py
dian/utils.py
dian.egg-info/PKG-INFO
dian.egg-info/SOURCES.txt
dian.egg-info/dependency_links.txt
dian.egg-info/entry_points.txt
dian.egg-info/requires.txt
dian.egg-info/top_level.txt
dian/devices/__init__.py
dian/devices/bus.py
dian/devices/devicebase.py
dian/devices/line.py
dian/devices/pqload.py
dian/devices/pvgen.py
dian/devices/shunt.py
docs/Makefile
docs/make.bat
docs/source/conf.py
docs/source/dian.devices.rst
docs/source/dian.rst
docs/source/index.rst
docs/source/installation.rst
docs/source/modules.rst
docs/source/release-history.rst
docs/source/usage.rst