Metadata-Version: 1.2
Name: dian
Version: 0.0.1
Summary: Power system simulator for data science
Home-page: https://github.com/cuihantao/dian
Author: Hantao Cui
Author-email: cuihantao@gmail.com
License: BSD (3-clause)
Platform: UNKNOWN
Classifier: Development Status :: 2 - Pre-Alpha
Classifier: Natural Language :: English
Classifier: Programming Language :: Python :: 3
Requires-Python: >=3.6
